<?xml version="1.0" encoding="UTF-8"?>
<flow xmlns="http://www.springframework.org/schema/webflow"
      xmlns:xsi="http://www.w3.org/2001/XMLSchema-instance"
      xsi:schemaLocation="http://www.springframework.org/schema/webflow
                          http://www.springframework.org/schema/webflow/spring-webflow-2.0.xsd">

	<secured authorities="ROLE_USER" />

	<persistence-context/>
	
	<input name="${id}" value="${flowScope.id}" />
	
	<on-start>
		<evaluate expression="${bookingService.findHotelById(flowScope.id)}" result="${flowScope.hotel}" />
		<evaluate expression="${hotel.createBooking(bookingService.findUser(currentUser.name))}" result="${flowScope.booking}" />
	</on-start>
	
	<view-state id="enterBookingDetails">
		<on-render>
			<evaluate expression="${bookingActions.setupForm}"/>
		</on-render>
		<transition on="proceed" to="reviewBooking">
			<evaluate expression="${bookingActions.bindAndValidate}" />
		</transition>
		<transition on="cancel" to="cancel" />
	</view-state>
	
	<view-state id="reviewBooking">
		<on-render>
			<evaluate expression="${bookingActions.setupForm}"/>
		</on-render>
		<transition on="confirm" to="bookingAuthorized">
			<evaluate expression="${entityManager.persist(booking)}" />
		</transition>
		<transition on="revise" to="enterBookingDetails" />
		<transition on="cancel" to="cancel" />
	</view-state>
	
	<end-state id="cancel"/>
	
	<end-state id="bookingAuthorized" commit="true" />
	
</flow>